aiostratum_proxy/__init__.py
aiostratum_proxy/application.py
aiostratum_proxy/errors.py
aiostratum_proxy/utils.py
aiostratum_proxy/protocols/__init__.py
aiostratum_proxy/protocols/equihash.py
aiostratum_proxy/protocols/stratum.py
aiostratum_proxy-1.1.dist-info/METADATA
aiostratum_proxy-1.1.dist-info/RECORD
aiostratum_proxy-1.1.dist-info/WHEEL
aiostratum_proxy-1.1.dist-info/entry_points.txt
aiostratum_proxy-1.1.dist-info/top_level.txt
