Metadata-Version: 2.1
Name: aiostratum-proxy
Version: 1.1
Summary: Python3 asyncio stratum protocol mining proxy
Home-page: https://github.com/wetblanketcc/aiostratum_proxy
Author: wetblanketcc
Author-email: 35851045+wetblanketcc@users.noreply.github.com
License: MIT
Keywords: async asyncio aio crypto cryptocurrency blockchain mining stratum protocol proxy pool equihash bitcoinlitecoin
Platform: UNKNOWN
Classifier: Development Status :: 4 - Beta
Classifier: Environment :: Web Environment
Classifier: Framework :: AsyncIO
Classifier: Intended Audience :: Financial and Insurance Industry
Classifier: Intended Audience :: Information Technology
Classifier: Intended Audience :: Science/Research
Classifier: Intended Audience :: System Administrators
Classifier: License :: OSI Approved :: MIT License
Classifier: Programming Language :: Python :: 3 :: Only
Classifier: Programming Language :: Python :: 3
Classifier: Programming Language :: Python :: 3.5
Classifier: Programming Language :: Python :: 3.6
Classifier: Programming Language :: Python :: 3.7
Classifier: Topic :: System :: Networking
Requires-Python: >=3.5
Requires-Dist: aiojsonrpc2 (==1.0.0)
Requires-Dist: PyYAML (==3.12)
